{
    "/js/app.js": "/js/app.js?id=9c05f0fc485e4e5fcada",
    "/css/app.css": "/css/app.css?id=5a3583b38df46d8e9a24",
    "/js/community.js": "/js/community.js?id=dd1d6fd0ff81c1e64ef7",
    "/js/contribute.js": "/js/contribute.js?id=2d409d25c5a95de2317f",
    "/js/discover.js": "/js/discover.js?id=1e846817fdd26166de6a",
    "/js/home.js": "/js/home.js?id=4d6ace911a8ffbfa56cf",
    "/js/post-form.js": "/js/post-form.js?id=ae942feac00c1ad248b1",
    "/js/profile.js": "/js/profile.js?id=089721174e144fa42719",
    "/js/profile-loves.js": "/js/profile-loves.js?id=7bdd0745e25bb039897d",
    "/js/profile-saves.js": "/js/profile-saves.js?id=2bcd32744a821f268f23",
    "/js/search.js": "/js/search.js?id=a2a560f1d57018034f38",
    "/js/setting.js": "/js/setting.js?id=36a12338661b65b4e8b2",
    "/js/single.js": "/js/single.js?id=f7e326466fbc1bc10ca0"
}
