{
    "/js/app.js": "/js/app.js",
    "/css/app.css": "/css/app.css",
    "/js/community.js": "/js/community.js",
    "/js/contribute.js": "/js/contribute.js",
    "/js/discover.js": "/js/discover.js",
    "/js/home.js": "/js/home.js",
    "/js/post-form.js": "/js/post-form.js",
    "/js/profile.js": "/js/profile.js",
    "/js/profile-loves.js": "/js/profile-loves.js",
    "/js/profile-saves.js": "/js/profile-saves.js",
    "/js/search.js": "/js/search.js",
    "/js/setting.js": "/js/setting.js",
    "/js/single.js": "/js/single.js"
}
